[
    {
        "components": "ENGINE AND ENGINE COOLING",
        "crash": false,
        "dateComplaintFiled": "04/21/2003",
        "dateOfIncident": "08/14/2002",
        "fire": false,
        "manufacturer": "Ford Motor Company",
        "numberOfDeaths": 0,
        "numberOfInjuries": 0,
        "odiNumber": 10016259,
        "products": [
            {
                "manufacturer": "Ford Motor Company",
                "productMake": "LINCOLN",
                "productModel": "LS",
                "productYear": "2002",
                "type": "Vehicle"
            }
        ],
        "summary": "2002 LS, UNDER SLOW SPEEDS AND MAKING A RIGHT TURN, VEHICLE SHUTS DOWN, INCLUDING POWER STEERING AND POWER BRAKES.  VEHICLE MUST COAST TO A STOP BEFORE ATTEMPTING TO RE-START ENGINE.    *JB",
        "vin": "1LNHM87A62Y"
    }
]