[
    {
        "components": "LATCHES/LOCKS/LINKAGES",
        "crash": false,
        "dateComplaintFiled": "05/01/2003",
        "dateOfIncident": "04/25/2003",
        "fire": false,
        "manufacturer": "Toyota Motor Corporation",
        "numberOfDeaths": 0,
        "numberOfInjuries": 0,
        "odiNumber": 10016883,
        "products": [
            {
                "manufacturer": "Toyota Motor Corporation",
                "productMake": "LEXUS",
                "productModel": "LS400",
                "productYear": "1990",
                "type": "Vehicle"
            }
        ],
        "summary": "PASSENGER DOOR LOCK MECHANISM ON MY 1990 LEXUS LS400 HAS FAILED TO THE POINT WHERE DOOR WILL NOT OPEN FROM OUTSIDE NOR INSIDE.  LEXUS DEALER WANTS $800 TO FIX THE PROBLEM AND THE POSSIBILITY OF DAMAGING DOOR PANEL AND SCRATCHING WINDOW.  THIS IS CLEARLY A SAFETY HAZARD THAT LEXUS (TOYOTA) SHOULD PAY FOR.  I HAVE ASKED THEM TO PAY FOR IT THEY REFUSED.  I AM ALSO ADDING THE FACT THAT THE DEALERSHIP HAS HAD OTHER LS400'S THAT THEY'VE FIXED FOR THIS SPECIFIC SAFETY PROBLEM.",
        "vin": "JT8UF11E5L0"
    }
]