[
    {
        "components": "SERVICE BRAKES, HYDRAULIC",
        "crash": false,
        "dateComplaintFiled": "04/29/2003",
        "dateOfIncident": "04/29/2003",
        "fire": false,
        "manufacturer": "Chrysler (FCA US, LLC)",
        "numberOfDeaths": 0,
        "numberOfInjuries": 0,
        "odiNumber": 10017822,
        "products": [
            {
                "manufacturer": "Chrysler (FCA US, LLC)",
                "productMake": "JEEP",
                "productModel": "WRANGLER",
                "productYear": "1991",
                "type": "Vehicle"
            }
        ],
        "summary": "THE CONSUMER RECEIVED A RECALL NOTICE (NUMBER B03) TO REPLACE THE BRAKE PEDAL ASSEMBLY.  A MONTH PAST AND THE PARTS WERE STILL NOT AVAILABLE FOR THE REPAIR.  *NLM",
        "vin": "PLEASE FILL"
    }
]