[
    {
        "components": "VISIBILITY,EQUIPMENT",
        "crash": false,
        "dateComplaintFiled": "07/03/2007",
        "dateOfIncident": "09/04/2004",
        "fire": false,
        "manufacturer": "General Motors, LLC",
        "numberOfDeaths": 0,
        "numberOfInjuries": 0,
        "odiNumber": 10195214,
        "products": [
            {
                "manufacturer": "General Motors, LLC",
                "productMake": "GMC",
                "productModel": "ENVOY",
                "productYear": "1999",
                "type": "Vehicle"
            },
            {
                "manufacturer": "General Motors, LLC",
                "productMake": "GMC",
                "productModel": "S SERIES",
                "productYear": "1995",
                "type": "Vehicle"
            }
        ],
        "summary": "I HAVE HAD TO REPLACE THE HEATER CORE 5 TIMES. THE FIRST TIME WAS 1 MONTH AFTER I PURCHASED THE JIMMY USED AT REEDMANS AUTO WORLD IN PA. 2 MONTHS AFTER THAT IT WAS REPLACED AGAIN  6 MONTHS LATER AND EVERY WINTER SINCE. I HAVE HEARD THERE WAS A IONIC PROBLEM WITH THE JIMMYS THAT SEND AND ELECTRICAL CURRENT THE MOTOR,  CAUSING THE HEATER CORES TO JUST EAT AWAY CAUSING THEM TO BE REPLACE. I HAVE ALSO HAD THE UPPER AND LOWER BALL JOINTS REPLACE SINCE I HAVE HAD THE JIMMY( THEY WERE ALSO REPLACED BY THE ORIGINAL OWNER. I HAVE HAD TO REPLACE THE ENGINE MOUNTS  AND MY READITOR SINCE THE  MOTOR MOUNTS BROKE AND SENT THE ENGINE THRU MY RADIATOR. ALL PROBLEMS WERE FIXED MOSTLY AT THE DEALER. HOWEVER. THE HEATER CORE HAS NOW BLOWN AGAIN I HAVE NO HEAT OR AIR. IF I TURN THEM ONE THE COOLANT GUSHES OUT OF THE CAR. I NO LONGER HAVE A EXTRA WARRANTY(EXPIRED 8/06) AND CANNOT GET IT FIXED..  NOTHING SEEMS TO CORRECT THE HEATER CORE  PROBLEM.  8AK",
        "vin": "1GKDT13W9X2"
    }
]