[
    {
        "components": "ELECTRICAL SYSTEM,AIR BAGS",
        "crash": false,
        "dateComplaintFiled": "04/09/2015",
        "dateOfIncident": "04/01/2015",
        "fire": false,
        "manufacturer": "General Motors, LLC",
        "numberOfDeaths": 0,
        "numberOfInjuries": 0,
        "odiNumber": 10704814,
        "products": [
            {
                "manufacturer": "General Motors, LLC",
                "productMake": "PONTIAC",
                "productModel": "G6",
                "productYear": "2008",
                "type": "Vehicle"
            }
        ],
        "summary": "PASSENGER OCCUPANT SENSOR, MALFUNCTION, I HAVE NO AIR BAGS ENABLED OR SEATBELT LOCKS DUE TO THIS FAILING IT'S 800 FOR THE WHOLE PART, PLUS LABOR OF 400. I HAVE EXTENDED WARRANT WHICH DON'T COVER THIS ISSUE. STATES SERVICE AIRBAG. WITHOUT THIS PROPERLY FIXED, THE CAR HAS NO SAFETY EQUIPMENT, AS IN AIRBAGS OR YOUR SEATBELTS LOCKING IN CASE OF A ACCIDENT.  *TR",
        "vin": "1G2ZG57N784"
    }
]