[
    {
        "components": "VEHICLE SPEED CONTROL",
        "crash": false,
        "dateComplaintFiled": "01/15/2003",
        "dateOfIncident": "01/15/2003",
        "fire": false,
        "manufacturer": "Ford Motor Company",
        "numberOfDeaths": 0,
        "numberOfInjuries": 0,
        "odiNumber": 10003971,
        "products": [
            {
                "manufacturer": "Ford Motor Company",
                "productMake": "FORD",
                "productModel": "EXPLORER",
                "productYear": "1998",
                "type": "Vehicle"
            }
        ],
        "summary": "WHILE DRIVING THE VEHICLE AT 65 MPH THE GAS PEDAL WELD BROKE.  THE DEALER WAS NOTIFIED BUT TOLD THE CONSUMER THAT THERE WAS NOTHING THEY COULD DO.  PLEASE PROVIDE ANY ADDITIONAL INFORMATION.   *NLM",
        "vin": "1FMDU32E3WC"
    }
]