[
    {
        "components": "ENGINE",
        "crash": false,
        "dateComplaintFiled": "06/23/2017",
        "dateOfIncident": "06/20/2017",
        "fire": false,
        "manufacturer": "Volkswagen Group of America, Inc.",
        "numberOfDeaths": 0,
        "numberOfInjuries": 0,
        "odiNumber": 11000862,
        "products": [
            {
                "manufacturer": "Volkswagen Group of America, Inc.",
                "productMake": "VOLKSWAGEN",
                "productModel": "ROUTAN",
                "productYear": "2013",
                "type": "Vehicle"
            }
        ],
        "summary": "TL* THE CONTACT OWNS A 2013 VOLKSWAGEN ROUTAN. WHILE DRIVING UNKNOWN SPEEDS, THE VEHICLE SHOOK, JERKED, AND MISFIRED WHILE THE ACCELERATOR PEDAL WAS APPLIED. THE VEHICLE WAS TAKEN TO A LOCAL DEALER (HAWK VOLKSWAGEN LOCATED AT 2861 W JEFFERSON ST JOLIET, IL 60435 815-741-1100) WHERE IT WAS DIAGNOSED THAT THE CYLINDER HEAD NEEDED TO BE REPLACED. THE VEHICLE WAS NOT REPAIRED. THE MANUFACTURER WAS NOTIFIED OF THE FAILURE, BUT DID NOT OFFER ANY ASSISTANCE. THE FAILURE MILEAGE WAS 74,000.",
        "vin": "2C4RVAAG5DR"
    }
]