[
    {
        "components": "ENGINE",
        "crash": false,
        "dateComplaintFiled": "07/11/2017",
        "dateOfIncident": "05/07/2017",
        "fire": false,
        "manufacturer": "Honda (American Honda Motor Co.)",
        "numberOfDeaths": 0,
        "numberOfInjuries": 0,
        "odiNumber": 11004207,
        "products": [
            {
                "manufacturer": "Honda (American Honda Motor Co.)",
                "productMake": "HONDA",
                "productModel": "ACCORD",
                "productYear": "2013",
                "type": "Vehicle"
            }
        ],
        "summary": "MY CARE IS CONSUMING TOO MUCH OIL. OIL LIGHT WARNING DOES NOT COME ON.",
        "vin": "1HGCR2F3XDA"
    }
]