[
    {
        "components": "AIR BAGS",
        "crash": false,
        "dateComplaintFiled": "06/21/2017",
        "dateOfIncident": "01/30/2016",
        "fire": false,
        "manufacturer": "Toyota Motor Corporation",
        "numberOfDeaths": 0,
        "numberOfInjuries": 0,
        "odiNumber": 11000467,
        "products": [
            {
                "manufacturer": "Toyota Motor Corporation",
                "productMake": "SCION",
                "productModel": "XB",
                "productYear": "2012",
                "type": "Vehicle"
            }
        ],
        "summary": "TL* THE CONTACT OWNS A 2012 SCION XB. THE CONTACT RECEIVED NOTIFICATION OF NHTSA CAMPAIGN NUMBER: 17V006000 (AIR BAGS); HOWEVER, THE PART TO DO THE RECALL REPAIR WAS NOT YET AVAILABLE. THE CONTACT STATED THAT THE MANUFACTURER EXCEEDED A REASONABLE AMOUNT OF TIME FOR THE RECALL REPAIR. SERVCO TOYOTA HONOLULU (LOCATED AT 2850 PUKOLOA STREET #200, HONOLULU, HI 96819) WAS CONTACTED REGARDING PART AVAILABILITY. THE CONTACT WAS INFORMED THAT THE MANUFACTURER WOULD SEND A SECOND NOTIFICATION WHEN THE REMEDY PARTS WERE AVAILABLE. THE MANUFACTURER WAS MADE AWARE OF THE ISSUE. THE CONTACT HAD NOT EXPERIENCED A FAILURE. VIN TOOL CONFIRMS PARTS NOT AVAILABLE.",
        "vin": "JTLZE4FE3CJ"
    }
]