[
    {
        "components": "SERVICE BRAKES",
        "crash": false,
        "dateComplaintFiled": "07/06/2017",
        "dateOfIncident": "07/01/2017",
        "fire": false,
        "manufacturer": "Nissan North America, Inc.",
        "numberOfDeaths": 0,
        "numberOfInjuries": 0,
        "odiNumber": 11003466,
        "products": [
            {
                "manufacturer": "Nissan North America, Inc.",
                "productMake": "INFINITI",
                "productModel": "QX50",
                "productYear": "2017",
                "type": "Vehicle"
            }
        ],
        "summary": "TL* THE CONTACT OWNS A 2017 INFINITY QX50. WHILE DRIVING APPROXIMATELY 45 MPH AND ATTEMPTING TO STOP, THE VEHICLE DID NOT IMMEDIATELY STOP WHEN DEPRESSING THE BRAKE PEDAL. AS A RESULT, A CRASH ALMOST OCCURRED. THE CONTACT INDICATED THAT THE FAILURE OCCURRED ON MULTIPLE OCCASIONS. THE VEHICLE WAS TAKEN TO RAMSEY INFINITI IN RAMSEY, NEW JERSEY, BUT THE FAILURE COULD NOT BE DUPLICATED. THE MANUFACTURER WAS NOTIFIED OF THE FAILURE. THE VIN WAS NOT AVAILABLE. THE FAILURE MILEAGE WAS 2,500.",
        "vin": ""
    }
]